rat_tools/__init__.py
rat_tools/all.py
rat_tools/ip.py
rat_tools/version.py
rat_tools_v2_shv-0.0.2.dist-info/METADATA
rat_tools_v2_shv-0.0.2.dist-info/WHEEL
rat_tools_v2_shv-0.0.2.dist-info/top_level.txt
rat_tools_v2_shv-0.0.2.dist-info/RECORD
