Metadata-Version: 2.4
Name: rat_tools_v2_shv
Version: 0.0.2
Summary: Rat Tools Create Rats With Ease
Author-email: SH_Dev <glock.96.beamed@gmail.com>
Requires-Python: >=3.7
Dynamic: requires-python
